pkgcore/__init__.py
pkgcore/_const.py
pkgcore/_verinfo.py
pkgcore/const.py
pkgcore/exceptions.py
pkgcore/gpg.py
pkgcore/log.py
pkgcore/os_data.py
pkgcore/plugin.py
pkgcore/binpkg/__init__.py
pkgcore/binpkg/remote.py
pkgcore/binpkg/repo_ops.py
pkgcore/binpkg/repository.py
pkgcore/binpkg/xpak.py
pkgcore/cache/__init__.py
pkgcore/cache/errors.py
pkgcore/cache/flat_hash.py
pkgcore/cache/fs_template.py
pkgcore/config/__init__.py
pkgcore/config/basics.py
pkgcore/config/central.py
pkgcore/config/cparser.py
pkgcore/config/domain.py
pkgcore/config/errors.py
pkgcore/config/hint.py
pkgcore/ebuild/__init__.py
pkgcore/ebuild/atom.py
pkgcore/ebuild/conditionals.py
pkgcore/ebuild/const.py
pkgcore/ebuild/cpv.py
pkgcore/ebuild/digest.py
pkgcore/ebuild/domain.py
pkgcore/ebuild/eapi.py
pkgcore/ebuild/ebd.py
pkgcore/ebuild/ebd_ipc.py
pkgcore/ebuild/ebuild_built.py
pkgcore/ebuild/ebuild_src.py
pkgcore/ebuild/eclass.py
pkgcore/ebuild/eclass_cache.py
pkgcore/ebuild/errors.py
pkgcore/ebuild/filter_env.py
pkgcore/ebuild/formatter.py
pkgcore/ebuild/inspect_profile.py
pkgcore/ebuild/misc.py
pkgcore/ebuild/pkg_updates.py
pkgcore/ebuild/portage_conf.py
pkgcore/ebuild/portageq.py
pkgcore/ebuild/processor.py
pkgcore/ebuild/profiles.py
pkgcore/ebuild/repo_objs.py
pkgcore/ebuild/repository.py
pkgcore/ebuild/resolver.py
pkgcore/ebuild/restricts.py
pkgcore/ebuild/triggers.py
pkgcore/fetch/__init__.py
pkgcore/fetch/base.py
pkgcore/fetch/custom.py
pkgcore/fetch/errors.py
pkgcore/fs/__init__.py
pkgcore/fs/contents.py
pkgcore/fs/fs.py
pkgcore/fs/livefs.py
pkgcore/fs/ops.py
pkgcore/fs/tar.py
pkgcore/merge/__init__.py
pkgcore/merge/const.py
pkgcore/merge/engine.py
pkgcore/merge/errors.py
pkgcore/merge/triggers.py
pkgcore/operations/__init__.py
pkgcore/operations/domain.py
pkgcore/operations/format.py
pkgcore/operations/observer.py
pkgcore/operations/regen.py
pkgcore/operations/repo.py
pkgcore/package/__init__.py
pkgcore/package/base.py
pkgcore/package/conditionals.py
pkgcore/package/errors.py
pkgcore-0.12.30.dist-info/entry_points.txt
pkgcore-0.12.30.dist-info/licenses/LICENSE
pkgcore-0.12.30.dist-info/WHEEL
pkgcore-0.12.30.dist-info/METADATA
pkgcore-0.12.30.dist-info/RECORD
