Metadata-Version: 2.4
Name: pkgcore
Version: 0.12.30
Summary: package managing framework
Author: Marien Zwart
Author-email: Michał Górny <mgorny@gentoo.org>, Tim Harder <radhermit@gmail.com>, Brian Harring <ferringb@gmail.com>, Arthur Zamarin <arthurzam@gentoo.org>
Maintainer-email: Arthur Zamarin <arthurzam@gentoo.org>
Requires-Python: ~=3.11
Classifier: License :: OSI Approved :: BSD License
Classifier: Programming Language :: Python :: 3.11
Classifier: Programming Language :: Python :: 3.12
Classifier: Programming Language :: Python :: 3.13
Classifier: Programming Language :: Python :: 3.14
License-File: LICENSE
Requires-Dist: snakeoil~=0.10.11
Requires-Dist: lxml
Requires-Dist: sphinx ; extra == "doc"
Requires-Dist: ruff ; extra == "formatter"
Requires-Dist: pytest>=6.0 ; extra == "test"
Requires-Dist: pytest-cov ; extra == "test"
Project-URL: Documentation, https://pkgcore.github.io/pkgcore/
Project-URL: Homepage, https://github.com/pkgcore/pkgcore
Project-URL: Source, https://github.com/pkgcore/pkgcore
Provides-Extra: doc
Provides-Extra: formatter
Provides-Extra: test
